qprof/__init__.py
qprof/_merge_dicts.py
qprof/data.py
qprof/frameworks.py
qprof/routine.py
qprof/routine_tree.py
qprof/exporters/BaseExporter.py
qprof/exporters/__init__.py
qprof/exporters/gprof/GprofExporter.py
qprof/exporters/gprof/__init__.py
qprof/exporters/gprof/strings.py
qprof/hardware/__init__.py
qprof/hardware/melbourne/__init__.py
qprof/hardware/melbourne/gate_times.py
qprof-1.4.0.dist-info/LICENSE
qprof-1.4.0.dist-info/METADATA
qprof-1.4.0.dist-info/WHEEL
qprof-1.4.0.dist-info/top_level.txt
qprof-1.4.0.dist-info/RECORD
