Metadata-Version: 2.1
Name: qprof
Version: 1.4.0
Summary: A quantum circuit profiling tool.
Home-page: UNKNOWN
Author: Adrien Suau
Author-email: adrien.suau@cerfacs.fr
License: UNKNOWN
Project-URL: Bug Reports, https://gitlab.com/qcomputing/qprof/qprof/issues
Project-URL: Source, https://gitlab.com/qcomputing/qprof/qprof
Project-URL: Collaborator, https://cerfacs.fr/en
Keywords: quantum,performance,gprof,profiling
Platform: UNKNOWN
Classifier: Development Status :: 3 - Alpha
Classifier: Intended Audience :: Developers
Classifier: Intended Audience :: Education
Classifier: Intended Audience :: Science/Research
Classifier: Topic :: Scientific/Engineering
Classifier: Topic :: Scientific/Engineering :: Mathematics
Classifier: License :: CeCILL-B Free Software License Agreement (CECILL-B)
Classifier: Natural Language :: English
Classifier: Operating System :: OS Independent
Classifier: Programming Language :: Python :: 3 :: Only
Requires-Dist: qprof-interfaces
Provides-Extra: all
Requires-Dist: black ; extra == 'all'
Requires-Dist: pygments ; extra == 'all'
Requires-Dist: setuptools ; extra == 'all'
Requires-Dist: wheel ; extra == 'all'
Requires-Dist: twine ; extra == 'all'
Requires-Dist: qprof-myqlm ; extra == 'all'
Requires-Dist: qprof-qiskit ; extra == 'all'
Requires-Dist: pytest ; extra == 'all'
Requires-Dist: pytest-cov ; extra == 'all'
Provides-Extra: all_plugins
Requires-Dist: qprof-myqlm ; extra == 'all_plugins'
Requires-Dist: qprof-qiskit ; extra == 'all_plugins'
Provides-Extra: dev
Requires-Dist: black ; extra == 'dev'
Requires-Dist: pygments ; extra == 'dev'
Requires-Dist: setuptools ; extra == 'dev'
Requires-Dist: wheel ; extra == 'dev'
Requires-Dist: twine ; extra == 'dev'
Provides-Extra: myqlm
Requires-Dist: qprof-myqlm ; extra == 'myqlm'
Provides-Extra: qat
Requires-Dist: qprof-myqlm ; extra == 'qat'
Provides-Extra: qiskit
Requires-Dist: qprof-qiskit ; extra == 'qiskit'
Provides-Extra: tests
Requires-Dist: pytest ; extra == 'tests'
Requires-Dist: pytest-cov ; extra == 'tests'
Requires-Dist: qprof-qiskit ; extra == 'tests'
